torda/__init__.py
torda/compare.py
torda/visualization.py
torda-0.1.6.3.dist-info/LICENSE
torda-0.1.6.3.dist-info/METADATA
torda-0.1.6.3.dist-info/WHEEL
torda-0.1.6.3.dist-info/top_level.txt
torda-0.1.6.3.dist-info/RECORD
