Metadata-Version: 2.1
Name: torda
Version: 0.1.6.3
Summary: Tools for Repetitive Data Analysis
Home-page: https://github.com/limyj0708/TORDA
Author: limyj0708
Author-email: limyj0708@gmail.com
License: MIT
Classifier: Programming Language :: Python :: 3
Classifier: License :: OSI Approved :: MIT License
Classifier: Operating System :: OS Independent
Requires-Python: >=3.8
License-File: LICENSE
Requires-Dist: plotly
Requires-Dist: scipy
Requires-Dist: scikit-learn
Requires-Dist: pandas
Requires-Dist: numpy
